README.md
setup.py
tec/__init__.py
tec.ic.ia.p1.g07.egg-info/PKG-INFO
tec.ic.ia.p1.g07.egg-info/SOURCES.txt
tec.ic.ia.p1.g07.egg-info/dependency_links.txt
tec.ic.ia.p1.g07.egg-info/top_level.txt
tec/ic/__init__.py
tec/ic/ia/__init__.py
tec/ic/ia/p1/__init__.py
tec/ic/ia/p1/g07.py
tec/ic/ia/p1/samples.py
tec/ic/ia/p1/models/Decision_Tree.py
tec/ic/ia/p1/models/K_Nearest_Neighbors.py
tec/ic/ia/p1/models/Logistic_Regression.py
tec/ic/ia/p1/models/Model.py
tec/ic/ia/p1/models/Neural_Network.py
tec/ic/ia/p1/models/Support_Vector_Machine.py
tec/ic/ia/p1/models/__init__.py
tec/ic/ia/pc1/__init__.py
tec/ic/ia/pc1/g07.py