Metadata-Version: 1.0
Name: tec.ic.ia.p1.g07
Version: 1.0.0
Summary: Programa que entrena distintos modelos de clasificacion de votantes para las elecciones presidenciales en Costa Rica 2018.
Home-page: https://github.com/mamemo/Voting-Prediction
Author: Trifuerza
Author-email: UNKNOWN
License: UNKNOWN
Platform: UNKNOWN
